{
  "recentFiles": [
    {
      "basename": "Профиль товара Чайный дневник",
      "path": "ТЗ Чайной/Страницы/Профили товаров/Профиль товара Чайный дневник.md"
    },
    {
      "basename": "Адрес доставки",
      "path": "ТЗ Чайной/Страницы/Профиль клиента/Адрес доставки.md"
    },
    {
      "basename": "Чайный дневник",
      "path": "ТЗ Чайной/Страницы/Профиль клиента/Чайный дневник.md"
    },
    {
      "basename": "История заказов",
      "path": "ТЗ Чайной/Страницы/Профиль клиента/История заказов.md"
    },
    {
      "basename": "Карточки товаров",
      "path": "ТЗ Чайной/Компоненты/Карточки товаров.md"
    },
    {
      "basename": "ЖЦ Заказа",
      "path": "ЖЦ объектов/ЖЦ Заказа.md"
    },
    {
      "basename": "Каталоги",
      "path": "ТЗ Чайной/Страницы/Каталоги.md"
    },
    {
      "basename": "Диаграммы последовательностей ролей Сбис",
      "path": "ТЗ Чайной/Диаграммы/Диаграммы последовательностей ролей Сбис.md"
    },
    {
      "basename": "Диаграммы интеграции со Сбис",
      "path": "Диаграммы интеграции со Сбис.canvas"
    },
    {
      "basename": "Диаграмма классов",
      "path": "ТЗ Чайной/Диаграммы/Диаграмма классов.md"
    }
  ],
  "omittedPaths": [],
  "omittedTags": [],
  "updateOn": "file-open",
  "omitBookmarks": false,
  "maxLength": 10
}